LICENSE.txt
MANIFEST.in
README.md
flask_whooshalchemy.py
requirements.txt
setup.cfg
setup.py
Flask_WhooshAlchemy_Redux.egg-info/PKG-INFO
Flask_WhooshAlchemy_Redux.egg-info/SOURCES.txt
Flask_WhooshAlchemy_Redux.egg-info/dependency_links.txt
Flask_WhooshAlchemy_Redux.egg-info/not-zip-safe
Flask_WhooshAlchemy_Redux.egg-info/pbr.json
Flask_WhooshAlchemy_Redux.egg-info/requires.txt
Flask_WhooshAlchemy_Redux.egg-info/top_level.txt
test/test_all.py