Metadata-Version: 1.1
Name: Flask-WhooshAlchemy-Redux
Version: 0.7.1
Summary: Whoosh extension to Flask/SQLAlchemy
Home-page: https://github.com/dhamaniasad/Flask-WhooshAlchemy
Author: Asad Dhamani
Author-email: dhamaniasad+code@gmail.com
License: BSD
Platform: any
Classifier: Environment :: Web Environment
Classifier: Intended Audience :: Developers
Classifier: License :: OSI Approved :: BSD License
Classifier: Operating System :: OS Independent
Classifier: Programming Language :: Python
Classifier: Topic :: Internet :: WWW/HTTP :: Dynamic Content
Classifier: Topic :: Software Development :: Libraries :: Python Modules
